docmaptools/__init__.py
docmaptools/convert.py
docmaptools/parse.py
docmaptools-0.28.0.dist-info/LICENSE
docmaptools-0.28.0.dist-info/METADATA
docmaptools-0.28.0.dist-info/WHEEL
docmaptools-0.28.0.dist-info/top_level.txt
docmaptools-0.28.0.dist-info/RECORD
